{
  "main": {
    "id": "b0ee537b466075f9",
    "type": "split",
    "children": [
      {
        "id": "c8fe7dabb501676f",
        "type": "tabs",
        "children": [
          {
            "id": "63bfb5c7328940a6",
            "type": "leaf",
            "state": {
              "type": "graph",
              "state": {},
              "icon": "lucide-git-fork",
              "title": "그래프 뷰"
            }
          }
        ]
      }
    ],
    "direction": "vertical"
  },
  "left": {
    "id": "39c6e98d6f1024a4",
    "type": "split",
    "children": [
      {
        "id": "b74b484667e79476",
        "type": "tabs",
        "children": [
          {
            "id": "409ceac1ebcab3ef",
            "type": "leaf",
            "state": {
              "type": "file-explorer",
              "state": {
                "sortOrder": "alphabetical",
                "autoReveal": false
              },
              "icon": "lucide-folder-closed",
              "title": "파일 탐색기"
            }
          },
          {
            "id": "aadef71b5a76cb35",
            "type": "leaf",
            "state": {
              "type": "search",
              "state": {
                "query": "",
                "matchingCase": false,
                "explainSearch": false,
                "collapseAll": false,
                "extraContext": false,
                "sortOrder": "alphabetical"
              },
              "icon": "lucide-search",
              "title": "검색"
            }
          },
          {
            "id": "08717048bca05118",
            "type": "leaf",
            "state": {
              "type": "bookmarks",
              "state": {},
              "icon": "lucide-bookmark",
              "title": "북마크"
            }
          }
        ]
      }
    ],
    "direction": "horizontal",
    "width": 300
  },
  "right": {
    "id": "bb655952dd38fd9c",
    "type": "split",
    "children": [
      {
        "id": "894c8fc863e67234",
        "type": "tabs",
        "children": [
          {
            "id": "e6a076e92863af13",
            "type": "leaf",
            "state": {
              "type": "backlink",
              "state": {
                "collapseAll": false,
                "extraContext": false,
                "sortOrder": "alphabetical",
                "showSearch": false,
                "searchQuery": "",
                "backlinkCollapsed": false,
                "unlinkedCollapsed": true
              },
              "icon": "links-coming-in",
              "title": "백링크"
            }
          },
          {
            "id": "0cc83aff82d5af70",
            "type": "leaf",
            "state": {
              "type": "outgoing-link",
              "state": {
                "linksCollapsed": false,
                "unlinkedCollapsed": true
              },
              "icon": "links-going-out",
              "title": "나가는 링크"
            }
          },
          {
            "id": "1302881bf5a4bd53",
            "type": "leaf",
            "state": {
              "type": "tag",
              "state": {
                "sortOrder": "frequency",
                "useHierarchy": true,
                "showSearch": false,
                "searchQuery": ""
              },
              "icon": "lucide-tags",
              "title": "태그"
            }
          },
          {
            "id": "ed89f2cfbe222867",
            "type": "leaf",
            "state": {
              "type": "outline",
              "state": {
                "followCursor": false,
                "showSearch": false,
                "searchQuery": ""
              },
              "icon": "lucide-list",
              "title": "개요"
            }
          }
        ]
      }
    ],
    "direction": "horizontal",
    "width": 300,
    "collapsed": true
  },
  "left-ribbon": {
    "hiddenItems": {
      "switcher:빠른 전환기 열기": false,
      "daily-notes:오늘의 일일 노트 열기": false,
      "bases:새 베이스 생성하기": false,
      "graph:그래프 뷰 열기": false,
      "canvas:새 캔버스 만들기": false,
      "templates:템플릿 삽입": false,
      "command-palette:명령어 팔레트 열기": false
    }
  },
  "active": "63bfb5c7328940a6",
  "lastOpenFiles": [
    "day05.md",
    "day06.md",
    "무제 파일.canvas",
    "day02.md",
    "day01.md",
    "day03.md"
  ]
}